{
  "title": "Maggie Montiel - Montiel Activewear | LinkedIn",
  "link": "https://www.linkedin.com/in/maggie-montiel-4ab197107/",
  "snippet": "· Experience: Montiel Activewear · Education: Indiana University Bloomington · Location: Los Angeles · 6 connections on LinkedIn. View Maggie Montiel’s profile on LinkedIn, a professional community of 1 billion ...",
  "mobile": null,
  "category": "Sportswear & Activewear",
  "scrapedAt": "2026-04-27T11:53:48.940Z",
  "fullName": "Maggie Montiel",
  "companyName": "Montiel Activewear"
}