{
	"id": "3annh0NpenPCKPu",
	"json": "{\"id\":\"3annh0NpenPCKPu\",\"url\":\"http://www.apparelgroupindiaprivate.com/about-us\",\"uniqueKey\":\"http://www.apparelgroupindiaprivate.com/about-us\",\"method\":\"GET\",\"noRetry\":false,\"retryCount\":0,\"errorMessages\":[],\"headers\":{},\"userData\":{\"domain\":\"apparelgroupindiaprivate.com\"}}",
	"method": "GET",
	"orderNo": 1777363554363,
	"retryCount": 0,
	"uniqueKey": "http://www.apparelgroupindiaprivate.com/about-us",
	"url": "http://www.apparelgroupindiaprivate.com/about-us"
}