{
	"id": "85B8UdmXhKPwEgA",
	"json": "{\"id\":\"85B8UdmXhKPwEgA\",\"url\":\"http://www.twinrealityarvrxrexperiences.com/about-us\",\"uniqueKey\":\"http://www.twinrealityarvrxrexperiences.com/about-us\",\"method\":\"GET\",\"noRetry\":false,\"retryCount\":0,\"errorMessages\":[],\"headers\":{},\"userData\":{\"domain\":\"twinrealityarvrxrexperiences.com\"}}",
	"method": "GET",
	"orderNo": 1777363554192,
	"retryCount": 0,
	"uniqueKey": "http://www.twinrealityarvrxrexperiences.com/about-us",
	"url": "http://www.twinrealityarvrxrexperiences.com/about-us"
}