{
	"id": "b5XMYh5RxdyGrdK",
	"json": "{\"id\":\"b5XMYh5RxdyGrdK\",\"url\":\"http://www.smartfrssolutionslinkedin.com\",\"uniqueKey\":\"http://www.smartfrssolutionslinkedin.com\",\"method\":\"GET\",\"noRetry\":false,\"retryCount\":0,\"errorMessages\":[],\"headers\":{},\"userData\":{\"domain\":\"smartfrssolutionslinkedin.com\"}}",
	"method": "GET",
	"orderNo": 1777363554111,
	"retryCount": 0,
	"uniqueKey": "http://www.smartfrssolutionslinkedin.com",
	"url": "http://www.smartfrssolutionslinkedin.com"
}