{
	"id": "inYPFUL0E4b8Ii9",
	"json": "{\"id\":\"inYPFUL0E4b8Ii9\",\"url\":\"http://www.caravaneventmanagement.com/contact\",\"uniqueKey\":\"http://www.caravaneventmanagement.com/contact\",\"method\":\"GET\",\"noRetry\":false,\"retryCount\":0,\"errorMessages\":[],\"headers\":{},\"userData\":{\"domain\":\"caravaneventmanagement.com\"}}",
	"method": "GET",
	"orderNo": 1777363554339,
	"retryCount": 0,
	"uniqueKey": "http://www.caravaneventmanagement.com/contact",
	"url": "http://www.caravaneventmanagement.com/contact"
}