{
	"id": "OhkmNefKzdzsSIm",
	"json": "{\"id\":\"OhkmNefKzdzsSIm\",\"url\":\"http://www.whovrtedxspeaker.com/contact-us\",\"uniqueKey\":\"http://www.whovrtedxspeaker.com/contact-us\",\"method\":\"GET\",\"noRetry\":false,\"retryCount\":0,\"errorMessages\":[],\"headers\":{},\"userData\":{\"domain\":\"whovrtedxspeaker.com\"}}",
	"method": "GET",
	"orderNo": 1777363554106,
	"retryCount": 0,
	"uniqueKey": "http://www.whovrtedxspeaker.com/contact-us",
	"url": "http://www.whovrtedxspeaker.com/contact-us"
}