{
	"id": "RITEGNQ6rtgvkiw",
	"json": "{\"id\":\"RITEGNQ6rtgvkiw\",\"url\":\"http://www.eventmanagementlinkedin.com/contact\",\"uniqueKey\":\"http://www.eventmanagementlinkedin.com/contact\",\"method\":\"GET\",\"noRetry\":false,\"retryCount\":0,\"errorMessages\":[],\"headers\":{},\"userData\":{\"domain\":\"eventmanagementlinkedin.com\"}}",
	"method": "GET",
	"orderNo": 1777363554336,
	"retryCount": 0,
	"uniqueKey": "http://www.eventmanagementlinkedin.com/contact",
	"url": "http://www.eventmanagementlinkedin.com/contact"
}