{
	"title": "Next",
	"link": "https://www.google.com/search?q=site:linkedin.com/in/+(%22CEO%22+OR+%22Founder%22+OR+%22Co-Founder%22+OR+%22Director%22+OR+%22Managing+Director%22+OR+%22Owner%22)+(%22Sports+Medicine%22+OR+%22Physiotherapy%22)+%22India%22&sca_esv=74e8f3377864fd67&ei=JGPwaaCROs3-5OUPvbac0Q8&start=100&sa=N&ved=2ahUKEwigs8qmhJCUAxVNP7kGHT0bJ_o4WhDw0wN6BAgoEBc",
	"snippet": "Page navigation\nPrevious\n\t\n5\n\t\n6\n\t\n7\n\t\n8\n\t\n9\n\t\n10\t\n11\n\t\n12\n\t\n13\n\t\n14",
	"mobile": null,
	"category": "Sports Medicine & Physiotherapy",
	"scrapedAt": "2026-04-28T07:35:31.669Z"
}