{
	"title": "Read more",
	"link": "https://in.linkedin.com/in/mohit-sondagar-090ab3245#:~:text=As%20the%20Founder%20%26%20CEO,advanced%20GPS%20and%20IoT%20solutions.&text=Aug%202021,Wheelseye%20GPS%20%26%20Fastag%20dippartment",
	"snippet": "Greater Surat Area · Founder · REFLECT TRACKERS\nAs the Founder & CEO of Reflect Trackers, I lead a technology-driven company ... Aug 2021 - Feb 2022 7 months. Surat, Gujarat, India. Sales Executive in ...",
	"mobile": null,
	"category": "Smart Wearables & Trackers",
	"scrapedAt": "2026-04-28T06:11:04.640Z"
}