{
	"title": "Next",
	"link": "https://www.google.com/search?q=site:linkedin.com/in/+(%22CEO%22+OR+%22Founder%22+OR+%22Co-Founder%22+OR+%22Director%22+OR+%22Managing+Director%22+OR+%22Owner%22)+(%22Smart+Wearables%22+OR+%22Trackers%22)+%22India%22&sca_esv=74e8f3377864fd67&ei=5F_waZU8hNXWxA_Uz8XxDQ&start=80&sa=N&ved=2ahUKEwiVvrOZgZCUAxWEqpUCHdRnMd44RhDw0wN6BAgfEBc",
	"snippet": "Page navigation\nPrevious\n\t\n3\n\t\n4\n\t\n5\n\t\n6\n\t\n7\n\t\n8\t\n9\n\t\n10\n\t\n11\n\t\n12",
	"mobile": null,
	"category": "Smart Wearables & Trackers",
	"scrapedAt": "2026-04-28T07:21:42.033Z"
}